README.md
setup.py
pingaz/__init__.py
pingaz/__main__.py
pingaz/asghosts.py
pingaz/cloudwatcher.py
pingaz/pinger.py
pingaz.egg-info/PKG-INFO
pingaz.egg-info/SOURCES.txt
pingaz.egg-info/dependency_links.txt
pingaz.egg-info/entry_points.txt
pingaz.egg-info/requires.txt
pingaz.egg-info/top_level.txt