Metadata-Version: 2.1
Name: pingaz
Version: 0.0.6
Summary: Monitor latency between AZs with fping and cloudwatch.
Home-page: https://github.com/lifeofguenter/pingaz
Author: Gunter Grodotzki
Author-email: gunter@grodotzki.co.za
License: UNKNOWN
Platform: UNKNOWN
Classifier: Programming Language :: Python :: 3
Classifier: License :: OSI Approved :: GNU General Public License v3 or later (GPLv3+)
Classifier: Operating System :: OS Independent
Requires-Python: >=3
